{"cues":[{"startAt":"5:00","duration":1000.0,"fadeTo":0.0,"type":"blackout"},{"startAt":"16:00","duration":1000.0,"fadeTo":0.0,"type":"vezer"},{"startAt":"22:00","duration":10000.0,"fadeTo":0.5070000290870667,"type":"normal"},{"startAt":"8:00","duration":10000.0,"fadeTo":1.0,"type":"normal"},{"startAt":"18:00","duration":1000.0,"fadeTo":0.0,"type":"vezer"},{"startAt":"19:00","duration":1000.0,"fadeTo":0.0,"type":"vezer"},{"startAt":"20:00","duration":1000.0,"fadeTo":0.0,"type":"vezer"},{"startAt":"12:00","duration":1000.0,"fadeTo":0.0,"type":"blackout"}]}